logic_explain_ml/xgboost.py
logicexplainml-0.1.1.dist-info/METADATA
logicexplainml-0.1.1.dist-info/WHEEL
logicexplainml-0.1.1.dist-info/top_level.txt
logicexplainml-0.1.1.dist-info/RECORD
