Metadata-Version: 2.4
Name: LogicExplainML
Version: 0.1.1
Summary: XAI explainers to Machine Learning Models
Author-email: Vinícius Peixoto <viniciuspxc@gmail.com>
License: MIT
Project-URL: Homepage, https://github.com/LogicExplainML-LEML/LogicExplainML
Project-URL: Repository, https://github.com/LogicExplainML-LEML/LogicExplainML
Project-URL: Issues, https://github.com/LogicExplainML-LEML/LogicExplainML/issues
Requires-Python: >=3.7
Requires-Dist: z3-solver
Requires-Dist: numpy
